{
  "project_info": {
    "project_number": "613066548408",
    "project_id": "igeoplus",
    "storage_bucket": "igeoplus.appspot.com"
  },
  "client": [
    {
      "client_info": {
        "mobilesdk_app_id": "1:613066548408:android:42c5f36ff82179deca404d",
        "android_client_info": {
          "package_name": "br.uff.igeo"
        }
      },
      "oauth_client": [
        {
          "client_id": "613066548408-2v5kdikuuvmpt7v946avh9qh443go058.apps.googleusercontent.com",
          "client_type": 3
        }
      ],
      "api_key": [
        {
          "current_key": "AIzaSyD2nXwIGMb7zvNkru56v8osTpVglYi_5y4"
        }
      ],
      "services": {
        "appinvite_service": {
          "other_platform_oauth_client": [
            {
              "client_id": "613066548408-2v5kdikuuvmpt7v946avh9qh443go058.apps.googleusercontent.com",
              "client_type": 3
            }
          ]
        }
      }
    }
  ],
  "configuration_version": "1"
}